{
  "openapi": "3.0.1",
  "info": {
    "title": "CobranzaApi",
    "version": "1.0"
  },
  "paths": {
    "/api/Clientes": {
      "get": {
        "tags": [
          "Clientes"
        ],
        "responses": {
          "200": {
            "description": "OK",
            "content": {
              "text/plain": {
                "schema": {
                  "type": "array",
                  "items": {
                    "$ref": "#/components/schemas/ClienteResumenDto"
                  }
                }
              },
              "application/json": {
                "schema": {
                  "type": "array",
                  "items": {
                    "$ref": "#/components/schemas/ClienteResumenDto"
                  }
                }
              },
              "text/json": {
                "schema": {
                  "type": "array",
                  "items": {
                    "$ref": "#/components/schemas/ClienteResumenDto"
                  }
                }
              }
            }
          }
        }
      }
    },
    "/api/Clientes/{codigoCliente}/operaciones": {
      "get": {
        "tags": [
          "Clientes"
        ],
        "parameters": [
          {
            "name": "codigoCliente",
            "in": "path",
            "required": true,
            "schema": {
              "type": "integer",
              "format": "int32"
            }
          }
        ],
        "responses": {
          "200": {
            "description": "OK",
            "content": {
              "text/plain": {
                "schema": {
                  "type": "array",
                  "items": {
                    "$ref": "#/components/schemas/Operacion"
                  }
                }
              },
              "application/json": {
                "schema": {
                  "type": "array",
                  "items": {
                    "$ref": "#/components/schemas/Operacion"
                  }
                }
              },
              "text/json": {
                "schema": {
                  "type": "array",
                  "items": {
                    "$ref": "#/components/schemas/Operacion"
                  }
                }
              }
            }
          }
        }
      }
    },
    "/api/IntencionPago": {
      "post": {
        "tags": [
          "IntencionPago"
        ],
        "requestBody": {
          "content": {
            "application/json": {
              "schema": {
                "$ref": "#/components/schemas/IntencionPagoRequest"
              }
            },
            "text/json": {
              "schema": {
                "$ref": "#/components/schemas/IntencionPagoRequest"
              }
            },
            "application/*+json": {
              "schema": {
                "$ref": "#/components/schemas/IntencionPagoRequest"
              }
            }
          }
        },
        "responses": {
          "200": {
            "description": "OK",
            "content": {
              "text/plain": {
                "schema": {
                  "$ref": "#/components/schemas/IntencionPagoResponse"
                }
              },
              "application/json": {
                "schema": {
                  "$ref": "#/components/schemas/IntencionPagoResponse"
                }
              },
              "text/json": {
                "schema": {
                  "$ref": "#/components/schemas/IntencionPagoResponse"
                }
              }
            }
          }
        }
      }
    }
  },
  "components": {
    "schemas": {
      "ClienteResumenDto": {
        "type": "object",
        "properties": {
          "codigoCliente": {
            "type": "integer",
            "format": "int32"
          },
          "nombreCompleto": {
            "type": "string",
            "nullable": true
          },
          "identificacionCliente": {
            "type": "string",
            "nullable": true
          },
          "tipoIdentificacion": {
            "type": "string",
            "nullable": true
          },
          "totalOperaciones": {
            "type": "integer",
            "format": "int32"
          },
          "mayorMora": {
            "type": "integer",
            "format": "int32"
          },
          "operacionMayorMora": {
            "type": "integer",
            "format": "int32"
          }
        },
        "additionalProperties": false
      },
      "IntencionPagoRequest": {
        "type": "object",
        "properties": {
          "codigoCliente": {
            "type": "integer",
            "format": "int32"
          },
          "operacionId": {
            "type": "integer",
            "format": "int32"
          },
          "montoPropuesto": {
            "type": "number",
            "format": "double"
          },
          "plazoMeses": {
            "type": "integer",
            "format": "int32"
          },
          "telefono": {
            "type": "string",
            "nullable": true
          },
          "correo": {
            "type": "string",
            "nullable": true
          },
          "observacion": {
            "type": "string",
            "nullable": true
          }
        },
        "additionalProperties": false
      },
      "IntencionPagoResponse": {
        "type": "object",
        "properties": {
          "ok": {
            "type": "boolean"
          },
          "mensaje": {
            "type": "string",
            "nullable": true
          },
          "numeroGestion": {
            "type": "string",
            "nullable": true
          }
        },
        "additionalProperties": false
      },
      "Operacion": {
        "type": "object",
        "properties": {
          "operacionId": {
            "type": "integer",
            "format": "int32"
          },
          "codigoCliente": {
            "type": "integer",
            "format": "int32"
          },
          "mora": {
            "type": "integer",
            "format": "int32"
          },
          "estado": {
            "type": "string",
            "nullable": true
          }
        },
        "additionalProperties": false
      }
    }
  }
}